influxgraph/__init__.py
influxgraph/_version.py
influxgraph/constants.py
influxgraph/templates.py
influxgraph/utils.py
influxgraph/classes/__init__.py
influxgraph/classes/finder.py
influxgraph/classes/leaf.py
influxgraph/classes/lock.py
influxgraph/classes/reader.py
influxgraph/classes/tree.py
influxgraph/ext/__init__.py
influxgraph/ext/nodetrie.so
influxgraph/ext/templates.c
influxgraph/ext/templates.so
influxgraph/ext/classes/__init__.py
influxgraph-1.5.0.post1.dist-info/LICENSE
influxgraph-1.5.0.post1.dist-info/METADATA
influxgraph-1.5.0.post1.dist-info/WHEEL
influxgraph-1.5.0.post1.dist-info/top_level.txt
influxgraph-1.5.0.post1.dist-info/RECORD
