Metadata-Version: 2.1
Name: influxgraph
Version: 1.5.0.post1
Summary: InfluxDB storage plugin for Graphite-API
Home-page: https://github.com/InfluxGraph/influxgraph
Author: Panos Kittenis
Author-email: 22e889d8@opayq.com
License: apache2
Platform: any
Classifier: Intended Audience :: Developers
Classifier: License :: OSI Approved :: Apache Software License
Classifier: Operating System :: OS Independent
Classifier: Programming Language :: Python
Classifier: Programming Language :: Python :: 2
Classifier: Programming Language :: Python :: 3
Classifier: Topic :: Scientific/Engineering :: Information Analysis
Classifier: Topic :: Scientific/Engineering :: Visualization
Classifier: Topic :: System :: Monitoring
Requires-Dist: influxdb (>=3.0.0)
Requires-Dist: graphite-api (>=1.1.2)
Requires-Dist: python-memcached
